./.gitignore
./README.md
./git_lexer.py
./pyproject.toml
./shellconsole_lexer.py
./shellconsole_style.py
./.github/workflows/publish-to-pypi.yml
./examples/git_lg.example
./examples/git_log.example
./examples/git_show.example
./examples/status.example
./examples/test.exmpl
./examples/test.sh
./test/__init__.py
./test/test_git.py
./test/test_git_branch.py
./test/test_git_log.py
./test/test_git_merge.py
./test/test_git_pretty_log.py
./test/test_git_show.py
./test/test_git_status.py
./test/test_prompts.py
pygments_shell_console-0.8.3.dist-info/METADATA
pygments_shell_console-0.8.3.dist-info/WHEEL
pygments_shell_console-0.8.3.dist-info/entry_points.txt
pygments_shell_console-0.8.3.dist-info/RECORD
