Metadata-Version: 2.4
Name: pygments-shell-console
Version: 0.8.3
Requires-Dist: pygments
